{
  "_id": {
    "$oid": "6156ba231fcf490b15de4ed5"
  },
  "level": "level_1_0",
  "isDefault": true,
  "answerText": [
    {
      "sticker": 40133
    },
    {
      "text": "бла бла бла"
    }
  ],
  "menu": {
    "Type": "keyboard",
    "Revision": 1,
    "Buttons": [
      {
        "Columns": 6,
        "Rows": 1,
        "BgColor": "#2db9b9",
        "Text": "Расписание сборов ИЮНЬ",
        "TextSize": "large",
        "ActionType": "reply",
        "ActionBody": "shedule_month_junior"
      },
      {
        "Columns": 6,
        "Rows": 1,
        "BgColor": "#adaeae",
        "Text": "Расписание на сегодня<br>(нет информации)",
        "TextSize": "large",
        "ActionType": "reply",
        "ActionBody": "shedule_today_junior"
      },
      {
        "Columns": 6,
        "Rows": 1,
        "BgColor": "#adaeae",
        "Text": "Расписание на завтра<br>(нет информации)",
        "TextSize": "large",
        "ActionType": "reply",
        "ActionBody": "shedule_tomorrow_junior"
      },
      {
        "Columns": 6,
        "Rows": 1,
        "BgColor": "#b8426b",
        "Text": "Вернуться для выбора (младшие/старшие)",
        "TextSize": "large",
        "ActionType": "reply",
        "ActionBody": "start"
      }
    ]
  }
}